electroPhysAnalysis/__init__.py
electroPhysAnalysis/gui.py
electrophysanalysis-0.1.0.dist-info/licenses/LICENSE
electrophysanalysis-0.1.0.dist-info/METADATA
electrophysanalysis-0.1.0.dist-info/WHEEL
electrophysanalysis-0.1.0.dist-info/entry_points.txt
electrophysanalysis-0.1.0.dist-info/top_level.txt
electrophysanalysis-0.1.0.dist-info/RECORD
